README.md
setup.cfg
setup.py
distributions/Binomialdistribution.py
distributions/Gaussiandistribution.py
distributions/Generaldistribution.py
distributions/__init__.py
marc4gov_distributions.egg-info/PKG-INFO
marc4gov_distributions.egg-info/SOURCES.txt
marc4gov_distributions.egg-info/dependency_links.txt
marc4gov_distributions.egg-info/not-zip-safe
marc4gov_distributions.egg-info/top_level.txt